CHANGELOG.rst
LICENSE
MANIFEST.in
README.rst
setup.py
examples/bucket.py
examples/bucket_policy.py
examples/custom_crypto.py
examples/download.py
examples/image.py
examples/live_channel.py
examples/object_basic.py
examples/object_callback.py
examples/object_check.py
examples/object_crypto.py
examples/object_extra.py
examples/object_post.py
examples/object_progress.py
examples/object_server_crypto.py
examples/select_csv.py
examples/sign_v2.py
examples/sts.py
examples/upload.py
oss2/__init__.py
oss2/api.py
oss2/auth.py
oss2/compat.py
oss2/crc64_combine.py
oss2/crypto.py
oss2/defaults.py
oss2/exceptions.py
oss2/headers.py
oss2/http.py
oss2/iterators.py
oss2/models.py
oss2/resumable.py
oss2/select_params.py
oss2/select_response.py
oss2/task_queue.py
oss2/utils.py
oss2/xml_utils.py
oss2_test.egg-info/PKG-INFO
oss2_test.egg-info/SOURCES.txt
oss2_test.egg-info/dependency_links.txt
oss2_test.egg-info/requires.txt
oss2_test.egg-info/top_level.txt
tests/__init__.py
tests/common.py
tests/test_api_base.py
tests/test_bucket.py
tests/test_chinese.py
tests/test_crc64_combine.py
tests/test_crypto.py
tests/test_download.py
tests/test_headers.py
tests/test_image.py
tests/test_init.py
tests/test_iterator.py
tests/test_live_channel.py
tests/test_mock_bucket.py
tests/test_mock_multipart.py
tests/test_mock_object.py
tests/test_multipart.py
tests/test_object.py
tests/test_select_csv_object.py
tests/test_select_json_object.py
tests/test_sts.py
tests/test_upload.py
tests/test_utils.py
unittests/__init__.py
unittests/common.py
unittests/test_bucket.py
unittests/test_iterator.py
unittests/test_multipart.py
unittests/test_object.py
unittests/test_resumable.py
unittests/test_select_object.py
unittests/test_task_queue.py